endpoint_logger/__init__.py
endpoint_logger/logging.py
endpoint_logger-1.0.1.dist-info/LICENCE
endpoint_logger-1.0.1.dist-info/METADATA
endpoint_logger-1.0.1.dist-info/WHEEL
endpoint_logger-1.0.1.dist-info/top_level.txt
endpoint_logger-1.0.1.dist-info/RECORD
